py_bpca/__init__.py
py_bpca/pyBPCA.py
py_bpca/runBPCA.py
py_bpca-0.0.3.dist-info/LICENSE
py_bpca-0.0.3.dist-info/METADATA
py_bpca-0.0.3.dist-info/WHEEL
py_bpca-0.0.3.dist-info/top_level.txt
py_bpca-0.0.3.dist-info/RECORD
