Metadata-Version: 2.1
Name: py-bpca
Version: 0.0.3
Summary: Python Bounded PCA
Home-page: http://github.com/RENCI/py_bpca
Author: Jeffery Tilson
Author-email: jtilson@renci.org
License: UNKNOWN
Keywords: pca bonded
Platform: Windows
Platform: Linux
Platform: Solaris
Platform: Mac OS-X
Platform: Unix
Classifier: Development Status :: 3 - Alpha
Classifier: Intended Audience :: Science/Research
Classifier: Intended Audience :: Developers
Classifier: Programming Language :: Python
Classifier: Programming Language :: Python :: 3
Classifier: Topic :: Software Development
Classifier: Topic :: Scientific/Engineering
Classifier: Operating System :: Unix
Classifier: Operating System :: POSIX :: Linux
Requires-Dist: markdown
Requires-Dist: numpy
Requires-Dist: pandas
Requires-Dist: scikit-learn
Requires-Dist: scipy
Requires-Dist: seaborn
